DESCRIPTION.rst
MANIFEST.in
README.rst
setup.cfg
setup.py
vaitk/__init__.py
vaitk/consts.py
vaitk/utils.py
vaitk.egg-info/PKG-INFO
vaitk.egg-info/SOURCES.txt
vaitk.egg-info/dependency_links.txt
vaitk.egg-info/not-zip-safe
vaitk.egg-info/top_level.txt
vaitk/core/VCoreApplication.py
vaitk/core/VEvent.py
vaitk/core/VObject.py
vaitk/core/VPoint.py
vaitk/core/VRect.py
vaitk/core/VSignal.py
vaitk/core/VSize.py
vaitk/core/VTimer.py
vaitk/core/VTimerEvent.py
vaitk/core/__init__.py
vaitk/gui/VApplication.py
vaitk/gui/VColor.py
vaitk/gui/VCursor.py
vaitk/gui/VGraphicElements.py
vaitk/gui/VPainter.py
vaitk/gui/VPalette.py
vaitk/gui/VScreen.py
vaitk/gui/VWidget.py
vaitk/gui/__init__.py
vaitk/gui/events.py
vaitk/gui/layouts.py
vaitk/gui/widgets/VDialog.py
vaitk/gui/widgets/VFrame.py
vaitk/gui/widgets/VLabel.py
vaitk/gui/widgets/VLineEdit.py
vaitk/gui/widgets/VProgressBar.py
vaitk/gui/widgets/VPushButton.py
vaitk/gui/widgets/VTabWidget.py
vaitk/gui/widgets/VToolTip.py
vaitk/gui/widgets/__init__.py
vaitk/test/VSignalSpy.py
vaitk/test/VTextScreen.py
vaitk/test/__init__.py