Metadata-Version: 1.1
Name: vaitk
Version: 1.7
Summary: VaiTk is a terminal-based graphical toolkit, similar to Qt
Home-page: https://github.com/stefanoborini/vaitk
Author: Stefano Borini
Author-email: stefano.borini@gmail.com
License: BSD
Keywords: library
Platform: UNKNOWN
Classifier: Development Status :: 3 - Alpha
Classifier: License :: OSI Approved :: BSD License
Classifier: Intended Audience :: Developers
Classifier: Programming Language :: Python :: 3.4
